sunflare/__init__.py
sunflare/config.py
sunflare/log.py
sunflare/py.typed
sunflare/containers/__init__.py
sunflare/containers/_registry.py
sunflare/engine/__init__.py
sunflare/engine/_exceptions.py
sunflare/engine/_status.py
sunflare/engine/_wrapper.py
sunflare/model/__init__.py
sunflare/model/_base.py
sunflare/model/_protocols.py
sunflare/presenter/__init__.py
sunflare/presenter/_base.py
sunflare/view/__init__.py
sunflare/view/_protocols.py
sunflare/view/qt/__init__.py
sunflare/virtual/__init__.py
sunflare/virtual/_bus.py
sunflare/virtual/_protocols.py
sunflare-0.8.1.dist-info/METADATA
sunflare-0.8.1.dist-info/WHEEL
sunflare-0.8.1.dist-info/licenses/LICENSE
sunflare-0.8.1.dist-info/RECORD
