Metadata-Version: 2.4
Name: sunflare
Version: 0.8.1
Summary: Redsun plugin development toolkit
Project-URL: bugs, https://github.com/redsun-acquisition/sunflare/issues
Project-URL: changelog, https://redsun-acquisition.github.io/sunflare/changelog/
Project-URL: homepage, https://github.com/redsun-acquisition/sunflare
Author-email: Jacopo Abramo <jacopo.abramo@gmail.com>
Maintainer-email: Jacopo Abramo <jacopo.abramo@gmail.com>
License: Apache-2.0
License-File: LICENSE
Classifier: Development Status :: 3 - Alpha
Classifier: Intended Audience :: Developers
Classifier: Intended Audience :: Science/Research
Classifier: License :: OSI Approved :: Apache Software License
Classifier: Programming Language :: Python :: 3
Classifier: Programming Language :: Python :: 3.10
Classifier: Programming Language :: Python :: 3.11
Classifier: Programming Language :: Python :: 3.12
Classifier: Programming Language :: Python :: 3.13
Classifier: Programming Language :: Python :: Implementation :: CPython
Classifier: Topic :: Software Development :: Libraries :: Python Modules
Classifier: Typing :: Typed
Requires-Python: >=3.10
Requires-Dist: attrs>=25.3.0
Requires-Dist: bluesky>=1.14.5
Requires-Dist: psygnal>=0.15.0
Requires-Dist: pyyaml>=6.0.2
Requires-Dist: typing-extensions>=4.14.0
Provides-Extra: pyqt
Requires-Dist: magicgui>=0.10.1; extra == 'pyqt'
Requires-Dist: pyqt6>=6.9.1; extra == 'pyqt'
Requires-Dist: qtpy>=2.4.3; extra == 'pyqt'
Provides-Extra: pyside
Requires-Dist: magicgui>=0.10.1; extra == 'pyside'
Requires-Dist: pyside6>=6.9.1; extra == 'pyside'
Requires-Dist: qtpy>=2.4.3; extra == 'pyside'
